ip_restriction/__init__.py
ip_restriction/middleware.py
tests/__init__.py
tests/admin.py
tests/decorators.py
tests/settings.py
tests/test_config.py
tests/test_middleware.py
tests/urls.py
tests/views.py
django_ip_restriction-1.1.1.dist-info/LICENSE
django_ip_restriction-1.1.1.dist-info/METADATA
django_ip_restriction-1.1.1.dist-info/WHEEL
django_ip_restriction-1.1.1.dist-info/top_level.txt
django_ip_restriction-1.1.1.dist-info/RECORD
